Wayload/__init__.py
Wayload/extract.py
Wayload/hide.py
Wayload-0.1.0.dist-info/METADATA
Wayload-0.1.0.dist-info/WHEEL
Wayload-0.1.0.dist-info/top_level.txt
Wayload-0.1.0.dist-info/RECORD
