Metadata-Version: 2.1
Name: Wayload
Version: 0.1.0
Summary: payload hide and extract module by W4lk3r
Home-page: https://github.com/Walker-00/Wayload
Author: W4lk3r
Author-email: w000alker@gmail.com
License: UNKNOWN
Project-URL: Bug Tracker, https://github.com/Walker-00/Wayload/issues
Keywords: payload,payload bind,payload extract
Platform: UNKNOWN
Classifier: Programming Language :: Python :: 3
Classifier: License :: OSI Approved :: MIT License
Classifier: Operating System :: Unix
Classifier: Operating System :: MacOS :: MacOS X
Classifier: Operating System :: Microsoft :: Windows
Requires-Python: >=3.6
Requires-Dist: requests
